efficient_apriori/__init__.py
efficient_apriori/apriori.py
efficient_apriori/itemsets.py
efficient_apriori/rules.py
efficient_apriori-2.0.6.dist-info/licenses/LICENSE
efficient_apriori-2.0.6.dist-info/METADATA
efficient_apriori-2.0.6.dist-info/WHEEL
efficient_apriori-2.0.6.dist-info/top_level.txt
efficient_apriori-2.0.6.dist-info/RECORD
