Metadata-Version: 2.4
Name: efficient_apriori
Version: 2.0.6
Summary:  An efficient Python implementation of the Apriori algorithm.
Author-email: tommyod <tommy.odland@gmail.com>
License: MIT License
Project-URL: Source, https://github.com/tommyod/Efficient-Apriori
Project-URL: Homepage, https://github.com/tommyod/Efficient-Apriori
Project-URL: Documentation, https://github.com/tommyod/Efficient-Apriori#readme
Project-URL: Repository, https://github.com/tommyod/Efficient-Apriori.git
Classifier: Development Status :: 5 - Production/Stable
Classifier: License :: OSI Approved :: MIT License
Classifier: Programming Language :: Python :: 3.9
Classifier: Programming Language :: Python :: 3.10
Classifier: Programming Language :: Python :: 3.11
Classifier: Programming Language :: Python :: 3.12
Classifier: Programming Language :: Python :: 3.13
Requires-Python: >=3.9
License-File: LICENSE
Dynamic: license-file
